{
  "cars": [
    {
      "id": "gmc",
      "featured": true,
      "year": 2021,
      "make": "GMC",
      "model": "Yukon XL Denali",
      "body": "Full-Size SUV",
      "price": 54900,
      "miles": "38,400",
      "trans": "10-Speed Auto",
      "drive": "4WD",
      "engine": "6.2L V8",
      "fuel": "Gasoline",
      "mpg": "14/19 mpg",
      "ext": "Onyx Black",
      "int": "Jet Black Leather",
      "images": ["images/gmc.jpg"],
      "features": [
        "Heated & ventilated leather seats",
        "Panoramic sunroof",
        "Bose premium audio",
        "Adaptive cruise control",
        "360° camera",
        "Power retractable running boards",
        "Wireless Apple CarPlay & Android Auto",
        "3rd-row seating"
      ],
      "desc": "Our flagship — a stunning Onyx Black Yukon XL Denali loaded with every premium feature. Three rows of room, a strong 6.2L V8, and a near-new interior."
    },
    {
      "id": "accent",
      "featured": false,
      "year": 2023,
      "make": "Hyundai",
      "model": "Accent",
      "body": "Sedan",
      "price": 15490,
      "miles": "26,100",
      "trans": "Automatic",
      "drive": "FWD",
      "engine": "1.5L 4-Cyl",
      "fuel": "Gasoline",
      "mpg": "33/41 mpg",
      "ext": "Polar White",
      "int": "Black Cloth",
      "images": ["images/accent.jpg"],
      "features": [
        "Apple CarPlay & Android Auto",
        "Backup camera",
        "Bluetooth & USB",
        "Cruise control",
        "Alloy wheels",
        "Keyless entry"
      ],
      "desc": "Clean, low-mileage, and easy on gas — a perfect first car, commuter, or reliable second vehicle. One owner and accident-free."
    },
    {
      "id": "civic",
      "featured": false,
      "year": 2016,
      "make": "Honda",
      "model": "Civic EX-T",
      "body": "Sedan",
      "price": 15490,
      "miles": "62,300",
      "trans": "Automatic (CVT)",
      "drive": "FWD",
      "engine": "1.5L Turbo 4-Cyl",
      "fuel": "Gasoline",
      "mpg": "31/40 mpg",
      "ext": "Modern Steel Gray",
      "int": "Black Cloth",
      "images": ["images/civic.jpg"],
      "features": [
        "1.5L Turbo engine",
        "Power moonroof",
        "Apple CarPlay & Android Auto",
        "Backup camera",
        "Remote start",
        "Push-button start",
        "Alloy wheels",
        "Dual-zone climate"
      ],
      "desc": "The turbocharged EX-T trim with the desirable moonroof and loads of features. Famous Honda reliability with great fuel economy. Freshly serviced."
    },
    {
      "id": "camry",
      "featured": false,
      "year": 2016,
      "make": "Toyota",
      "model": "Camry SE",
      "body": "Sedan",
      "price": 14290,
      "miles": "71,800",
      "trans": "6-Speed Auto",
      "drive": "FWD",
      "engine": "2.5L 4-Cyl",
      "fuel": "Gasoline",
      "mpg": "25/35 mpg",
      "ext": "Celestial Silver",
      "int": "Black Sport Cloth",
      "images": ["images/camry.jpg"],
      "features": [
        "Sport-tuned suspension",
        "Paddle shifters",
        "Touchscreen audio",
        "Backup camera",
        "Dual-zone climate",
        "Alloy wheels",
        "Keyless entry"
      ],
      "desc": "The sporty SE trim of the legendarily dependable Camry. Roomy, comfortable, and built to run for years. One previous owner."
    }
  ]
}
